flake8_builtins.py
flake8_builtins_unleashed-1.3.1.dist-info/DESCRIPTION.rst
flake8_builtins_unleashed-1.3.1.dist-info/METADATA
flake8_builtins_unleashed-1.3.1.dist-info/RECORD
flake8_builtins_unleashed-1.3.1.dist-info/WHEEL
flake8_builtins_unleashed-1.3.1.dist-info/entry_points.txt
flake8_builtins_unleashed-1.3.1.dist-info/metadata.json
flake8_builtins_unleashed-1.3.1.dist-info/top_level.txt
