Metadata-Version: 2.0
Name: flake8-builtins-unleashed
Version: 1.3.1
Summary: builtin override checker plugin for flake8
Home-page: https://github.com/vikingco/flake8-builtins
Author: VikingCo NV
Author-email: technology@vikingco.com
License: MIT
Keywords: flake8 builtins
Platform: UNKNOWN
Classifier: Development Status :: 3 - Alpha
Classifier: Environment :: Console
Classifier: Intended Audience :: Developers
Classifier: License :: OSI Approved :: MIT License
Classifier: Operating System :: OS Independent
Classifier: Programming Language :: Python
Classifier: Programming Language :: Python :: 2
Classifier: Programming Language :: Python :: 3
Classifier: Topic :: Software Development :: Libraries :: Python Modules
Classifier: Topic :: Software Development :: Quality Assurance
Requires-Dist: flake8
